ypstruct/__init__.py
ypstruct-0.0.1.dist-info/METADATA
ypstruct-0.0.1.dist-info/RECORD
ypstruct-0.0.1.dist-info/WHEEL
ypstruct-0.0.1.dist-info/top_level.txt
