Metadata-Version: 1.1
Name: ypstruct
Version: 0.0.1
Summary: A simple and easy-to-use C-like structure for Python
Home-page: https://github.com/smkalami/ypstruct
Author: Mostapha Kalami Heris
Author-email: sm.kalami@gmail.com
License: UNKNOWN
Platform: UNKNOWN
Classifier: Programming Language :: Python :: 3
Classifier: License :: OSI Approved :: MIT License
Classifier: Operating System :: OS Independent
